{
	"completely_empty": false,
	"image": {
		"height": 243,
		"scale": 4.012345679012346,
		"width": 232
	},
	"mark": [
		{
			"class_idx": 0,
			"name": "bt",
			"points": [
				{
					"int_x": 186,
					"int_y": 152,
					"x": 0.8012889366272825,
					"y": 0.6256410256410256
				},
				{
					"int_x": 193,
					"int_y": 152,
					"x": 0.8313641245972073,
					"y": 0.6256410256410256
				},
				{
					"int_x": 193,
					"int_y": 157,
					"x": 0.8313641245972073,
					"y": 0.6461538461538461
				},
				{
					"int_x": 186,
					"int_y": 157,
					"x": 0.8012889366272825,
					"y": 0.6461538461538461
				}
			],
			"rect": {
				"h": 0.02051282051282044,
				"int_h": 6,
				"int_w": 8,
				"int_x": 186,
				"int_y": 152,
				"w": 0.03007518796992481,
				"x": 0.8012889366272825,
				"y": 0.6256410256410256
			}
		},
		{
			"class_idx": 0,
			"name": "bt",
			"points": [
				{
					"int_x": 194,
					"int_y": 157,
					"x": 0.8361976369495167,
					"y": 0.6441025641025642
				},
				{
					"int_x": 200,
					"int_y": 157,
					"x": 0.8609022556390978,
					"y": 0.6441025641025642
				},
				{
					"int_x": 200,
					"int_y": 163,
					"x": 0.8609022556390978,
					"y": 0.6707692307692308
				},
				{
					"int_x": 194,
					"int_y": 163,
					"x": 0.8361976369495167,
					"y": 0.6707692307692308
				}
			],
			"rect": {
				"h": 0.026666666666666616,
				"int_h": 7,
				"int_w": 7,
				"int_x": 194,
				"int_y": 157,
				"w": 0.02470461868958118,
				"x": 0.8361976369495167,
				"y": 0.6441025641025642
			}
		},
		{
			"class_idx": 0,
			"name": "bt",
			"points": [
				{
					"int_x": 204,
					"int_y": 166,
					"x": 0.8775510204081632,
					"y": 0.6851282051282052
				},
				{
					"int_x": 210,
					"int_y": 166,
					"x": 0.9054779806659506,
					"y": 0.6851282051282052
				},
				{
					"int_x": 210,
					"int_y": 175,
					"x": 0.9054779806659506,
					"y": 0.722051282051282
				},
				{
					"int_x": 204,
					"int_y": 175,
					"x": 0.8775510204081632,
					"y": 0.722051282051282
				}
			],
			"rect": {
				"h": 0.036923076923076836,
				"int_h": 10,
				"int_w": 7,
				"int_x": 204,
				"int_y": 166,
				"w": 0.027926960257787403,
				"x": 0.8775510204081632,
				"y": 0.6851282051282052
			}
		},
		{
			"class_idx": 0,
			"name": "bt",
			"points": [
				{
					"int_x": 194,
					"int_y": 182,
					"x": 0.835123523093448,
					"y": 0.7497435897435897
				},
				{
					"int_x": 200,
					"int_y": 182,
					"x": 0.864124597207304,
					"y": 0.7497435897435897
				},
				{
					"int_x": 200,
					"int_y": 189,
					"x": 0.864124597207304,
					"y": 0.7784615384615384
				},
				{
					"int_x": 194,
					"int_y": 189,
					"x": 0.835123523093448,
					"y": 0.7784615384615384
				}
			],
			"rect": {
				"h": 0.02871794871794875,
				"int_h": 8,
				"int_w": 7,
				"int_x": 194,
				"int_y": 182,
				"w": 0.029001074113855996,
				"x": 0.835123523093448,
				"y": 0.7497435897435897
			}
		},
		{
			"class_idx": 0,
			"name": "bt",
			"points": [
				{
					"int_x": 201,
					"int_y": 183,
					"x": 0.8668098818474759,
					"y": 0.7533333333333333
				},
				{
					"int_x": 209,
					"int_y": 183,
					"x": 0.8990332975295381,
					"y": 0.7533333333333333
				},
				{
					"int_x": 209,
					"int_y": 190,
					"x": 0.8990332975295381,
					"y": 0.781025641025641
				},
				{
					"int_x": 201,
					"int_y": 190,
					"x": 0.8668098818474759,
					"y": 0.781025641025641
				}
			],
			"rect": {
				"h": 0.027692307692307683,
				"int_h": 8,
				"int_w": 9,
				"int_x": 201,
				"int_y": 183,
				"w": 0.03222341568206222,
				"x": 0.8668098818474759,
				"y": 0.7533333333333333
			}
		},
		{
			"class_idx": 0,
			"name": "bt",
			"points": [
				{
					"int_x": 204,
					"int_y": 190,
					"x": 0.8813104189044039,
					"y": 0.7830769230769231
				},
				{
					"int_x": 214,
					"int_y": 190,
					"x": 0.9232008592910848,
					"y": 0.7830769230769231
				},
				{
					"int_x": 214,
					"int_y": 201,
					"x": 0.9232008592910848,
					"y": 0.8251282051282051
				},
				{
					"int_x": 204,
					"int_y": 201,
					"x": 0.8813104189044039,
					"y": 0.8251282051282051
				}
			],
			"rect": {
				"h": 0.042051282051281946,
				"int_h": 12,
				"int_w": 11,
				"int_x": 204,
				"int_y": 190,
				"w": 0.04189044038668088,
				"x": 0.8813104189044039,
				"y": 0.7830769230769231
			}
		},
		{
			"class_idx": 0,
			"name": "bt",
			"points": [
				{
					"int_x": 189,
					"int_y": 190,
					"x": 0.813641245972073,
					"y": 0.7830769230769231
				},
				{
					"int_x": 195,
					"int_y": 190,
					"x": 0.8404940923737916,
					"y": 0.7830769230769231
				},
				{
					"int_x": 195,
					"int_y": 197,
					"x": 0.8404940923737916,
					"y": 0.8087179487179487
				},
				{
					"int_x": 189,
					"int_y": 197,
					"x": 0.813641245972073,
					"y": 0.8087179487179487
				}
			],
			"rect": {
				"h": 0.02564102564102555,
				"int_h": 8,
				"int_w": 7,
				"int_x": 189,
				"int_y": 190,
				"w": 0.02685284640171859,
				"x": 0.813641245972073,
				"y": 0.7830769230769231
			}
		},
		{
			"class_idx": 0,
			"name": "bt",
			"points": [
				{
					"int_x": 189,
					"int_y": 168,
					"x": 0.8141783029001074,
					"y": 0.6933333333333334
				},
				{
					"int_x": 193,
					"int_y": 168,
					"x": 0.8335123523093447,
					"y": 0.6933333333333334
				},
				{
					"int_x": 193,
					"int_y": 176,
					"x": 0.8335123523093447,
					"y": 0.7261538461538461
				},
				{
					"int_x": 189,
					"int_y": 176,
					"x": 0.8141783029001074,
					"y": 0.7261538461538461
				}
			],
			"rect": {
				"h": 0.03282051282051279,
				"int_h": 9,
				"int_w": 5,
				"int_x": 189,
				"int_y": 168,
				"w": 0.01933404940923733,
				"x": 0.8141783029001074,
				"y": 0.6933333333333334
			}
		},
		{
			"class_idx": 0,
			"name": "bt",
			"points": [
				{
					"int_x": 175,
					"int_y": 177,
					"x": 0.7556390977443609,
					"y": 0.7297435897435897
				},
				{
					"int_x": 183,
					"int_y": 177,
					"x": 0.7889366272824919,
					"y": 0.7297435897435897
				},
				{
					"int_x": 183,
					"int_y": 182,
					"x": 0.7889366272824919,
					"y": 0.7492307692307693
				},
				{
					"int_x": 175,
					"int_y": 182,
					"x": 0.7556390977443609,
					"y": 0.7492307692307693
				}
			],
			"rect": {
				"h": 0.019487179487179596,
				"int_h": 6,
				"int_w": 9,
				"int_x": 175,
				"int_y": 177,
				"w": 0.03329752953813103,
				"x": 0.7556390977443609,
				"y": 0.7297435897435897
			}
		},
		{
			"class_idx": 0,
			"name": "bt",
			"points": [
				{
					"int_x": 161,
					"int_y": 172,
					"x": 0.6938775510204082,
					"y": 0.7092307692307692
				},
				{
					"int_x": 170,
					"int_y": 172,
					"x": 0.7346938775510204,
					"y": 0.7092307692307692
				},
				{
					"int_x": 170,
					"int_y": 180,
					"x": 0.7346938775510204,
					"y": 0.741025641025641
				},
				{
					"int_x": 161,
					"int_y": 180,
					"x": 0.6938775510204082,
					"y": 0.741025641025641
				}
			],
			"rect": {
				"h": 0.031794871794871726,
				"int_h": 9,
				"int_w": 10,
				"int_x": 161,
				"int_y": 172,
				"w": 0.04081632653061229,
				"x": 0.6938775510204082,
				"y": 0.7092307692307692
			}
		},
		{
			"class_idx": 0,
			"name": "bt",
			"points": [
				{
					"int_x": 163,
					"int_y": 182,
					"x": 0.7030075187969925,
					"y": 0.7492307692307691
				},
				{
					"int_x": 168,
					"int_y": 182,
					"x": 0.7255639097744361,
					"y": 0.7492307692307691
				},
				{
					"int_x": 168,
					"int_y": 187,
					"x": 0.7255639097744361,
					"y": 0.7687179487179487
				},
				{
					"int_x": 163,
					"int_y": 187,
					"x": 0.7030075187969925,
					"y": 0.7687179487179487
				}
			],
			"rect": {
				"h": 0.019487179487179596,
				"int_h": 6,
				"int_w": 6,
				"int_x": 163,
				"int_y": 182,
				"w": 0.022556390977443552,
				"x": 0.7030075187969925,
				"y": 0.7492307692307691
			}
		},
		{
			"class_idx": 0,
			"name": "bt",
			"points": [
				{
					"int_x": 169,
					"int_y": 185,
					"x": 0.7287862513426424,
					"y": 0.7610256410256411
				},
				{
					"int_x": 176,
					"int_y": 185,
					"x": 0.7577873254564984,
					"y": 0.7610256410256411
				},
				{
					"int_x": 176,
					"int_y": 190,
					"x": 0.7577873254564984,
					"y": 0.7815384615384615
				},
				{
					"int_x": 169,
					"int_y": 190,
					"x": 0.7287862513426424,
					"y": 0.7815384615384615
				}
			],
			"rect": {
				"h": 0.02051282051282044,
				"int_h": 6,
				"int_w": 8,
				"int_x": 169,
				"int_y": 185,
				"w": 0.029001074113855996,
				"x": 0.7287862513426424,
				"y": 0.7610256410256411
			}
		},
		{
			"class_idx": 0,
			"name": "bt",
			"points": [
				{
					"int_x": 188,
					"int_y": 214,
					"x": 0.8114930182599356,
					"y": 0.8815384615384615
				},
				{
					"int_x": 195,
					"int_y": 214,
					"x": 0.8404940923737916,
					"y": 0.8815384615384615
				},
				{
					"int_x": 195,
					"int_y": 220,
					"x": 0.8404940923737916,
					"y": 0.9051282051282051
				},
				{
					"int_x": 188,
					"int_y": 220,
					"x": 0.8114930182599356,
					"y": 0.9051282051282051
				}
			],
			"rect": {
				"h": 0.02358974358974364,
				"int_h": 7,
				"int_w": 8,
				"int_x": 188,
				"int_y": 214,
				"w": 0.029001074113855996,
				"x": 0.8114930182599356,
				"y": 0.8815384615384615
			}
		},
		{
			"class_idx": 0,
			"name": "bt",
			"points": [
				{
					"int_x": 204,
					"int_y": 208,
					"x": 0.8780880773361976,
					"y": 0.8553846153846154
				},
				{
					"int_x": 210,
					"int_y": 208,
					"x": 0.9049409237379162,
					"y": 0.8553846153846154
				},
				{
					"int_x": 210,
					"int_y": 213,
					"x": 0.9049409237379162,
					"y": 0.8758974358974358
				},
				{
					"int_x": 204,
					"int_y": 213,
					"x": 0.8780880773361976,
					"y": 0.8758974358974358
				}
			],
			"rect": {
				"h": 0.02051282051282044,
				"int_h": 6,
				"int_w": 7,
				"int_x": 204,
				"int_y": 208,
				"w": 0.02685284640171859,
				"x": 0.8780880773361976,
				"y": 0.8553846153846154
			}
		},
		{
			"class_idx": 0,
			"name": "bt",
			"points": [
				{
					"int_x": 183,
					"int_y": 132,
					"x": 0.7894736842105263,
					"y": 0.5451282051282051
				},
				{
					"int_x": 189,
					"int_y": 132,
					"x": 0.8131041890440387,
					"y": 0.5451282051282051
				},
				{
					"int_x": 189,
					"int_y": 139,
					"x": 0.8131041890440387,
					"y": 0.5728205128205128
				},
				{
					"int_x": 183,
					"int_y": 139,
					"x": 0.7894736842105263,
					"y": 0.5728205128205128
				}
			],
			"rect": {
				"h": 0.027692307692307683,
				"int_h": 8,
				"int_w": 7,
				"int_x": 183,
				"int_y": 132,
				"w": 0.023630504833512367,
				"x": 0.7894736842105263,
				"y": 0.5451282051282051
			}
		},
		{
			"class_idx": 0,
			"name": "bt",
			"points": [
				{
					"int_x": 164,
					"int_y": 126,
					"x": 0.7073039742212675,
					"y": 0.5205128205128204
				},
				{
					"int_x": 175,
					"int_y": 126,
					"x": 0.7534908700322234,
					"y": 0.5205128205128204
				},
				{
					"int_x": 175,
					"int_y": 134,
					"x": 0.7534908700322234,
					"y": 0.5502564102564103
				},
				{
					"int_x": 164,
					"int_y": 134,
					"x": 0.7073039742212675,
					"y": 0.5502564102564103
				}
			],
			"rect": {
				"h": 0.029743589743589816,
				"int_h": 9,
				"int_w": 12,
				"int_x": 164,
				"int_y": 126,
				"w": 0.04618689581095592,
				"x": 0.7073039742212675,
				"y": 0.5205128205128204
			}
		},
		{
			"class_idx": 0,
			"name": "bt",
			"points": [
				{
					"int_x": 166,
					"int_y": 114,
					"x": 0.7175080558539205,
					"y": 0.4671794871794872
				},
				{
					"int_x": 172,
					"int_y": 114,
					"x": 0.7432867883995703,
					"y": 0.4671794871794872
				},
				{
					"int_x": 172,
					"int_y": 122,
					"x": 0.7432867883995703,
					"y": 0.5030769230769231
				},
				{
					"int_x": 166,
					"int_y": 122,
					"x": 0.7175080558539205,
					"y": 0.5030769230769231
				}
			],
			"rect": {
				"h": 0.03589743589743588,
				"int_h": 9,
				"int_w": 7,
				"int_x": 166,
				"int_y": 114,
				"w": 0.025778732545649774,
				"x": 0.7175080558539205,
				"y": 0.4671794871794872
			}
		},
		{
			"class_idx": 0,
			"name": "bt",
			"points": [
				{
					"int_x": 173,
					"int_y": 113,
					"x": 0.7448979591836735,
					"y": 0.4646153846153846
				},
				{
					"int_x": 180,
					"int_y": 113,
					"x": 0.7738990332975295,
					"y": 0.4646153846153846
				},
				{
					"int_x": 180,
					"int_y": 122,
					"x": 0.7738990332975295,
					"y": 0.5015384615384615
				},
				{
					"int_x": 173,
					"int_y": 122,
					"x": 0.7448979591836735,
					"y": 0.5015384615384615
				}
			],
			"rect": {
				"h": 0.03692307692307689,
				"int_h": 10,
				"int_w": 8,
				"int_x": 173,
				"int_y": 113,
				"w": 0.029001074113855996,
				"x": 0.7448979591836735,
				"y": 0.4646153846153846
			}
		},
		{
			"class_idx": 0,
			"name": "bt",
			"points": [
				{
					"int_x": 158,
					"int_y": 101,
					"x": 0.6831364124597208,
					"y": 0.41589743589743594
				},
				{
					"int_x": 166,
					"int_y": 101,
					"x": 0.715359828141783,
					"y": 0.41589743589743594
				},
				{
					"int_x": 166,
					"int_y": 106,
					"x": 0.715359828141783,
					"y": 0.43743589743589745
				},
				{
					"int_x": 158,
					"int_y": 106,
					"x": 0.6831364124597208,
					"y": 0.43743589743589745
				}
			],
			"rect": {
				"h": 0.021538461538461506,
				"int_h": 6,
				"int_w": 9,
				"int_x": 158,
				"int_y": 101,
				"w": 0.03222341568206222,
				"x": 0.6831364124597208,
				"y": 0.41589743589743594
			}
		},
		{
			"class_idx": 0,
			"name": "bt",
			"points": [
				{
					"int_x": 148,
					"int_y": 101,
					"x": 0.6364124597207305,
					"y": 0.41538461538461535
				},
				{
					"int_x": 157,
					"int_y": 101,
					"x": 0.6761546723952739,
					"y": 0.41538461538461535
				},
				{
					"int_x": 157,
					"int_y": 110,
					"x": 0.6761546723952739,
					"y": 0.4523076923076923
				},
				{
					"int_x": 148,
					"int_y": 110,
					"x": 0.6364124597207305,
					"y": 0.4523076923076923
				}
			],
			"rect": {
				"h": 0.03692307692307695,
				"int_h": 10,
				"int_w": 10,
				"int_x": 148,
				"int_y": 101,
				"w": 0.039742212674543476,
				"x": 0.6364124597207305,
				"y": 0.41538461538461535
			}
		},
		{
			"class_idx": 0,
			"name": "bt",
			"points": [
				{
					"int_x": 147,
					"int_y": 84,
					"x": 0.631578947368421,
					"y": 0.3466666666666667
				},
				{
					"int_x": 155,
					"int_y": 84,
					"x": 0.6659505907626209,
					"y": 0.3466666666666667
				},
				{
					"int_x": 155,
					"int_y": 93,
					"x": 0.6659505907626209,
					"y": 0.3815384615384615
				},
				{
					"int_x": 147,
					"int_y": 93,
					"x": 0.631578947368421,
					"y": 0.3815384615384615
				}
			],
			"rect": {
				"h": 0.034871794871794815,
				"int_h": 10,
				"int_w": 9,
				"int_x": 147,
				"int_y": 84,
				"w": 0.03437164339419985,
				"x": 0.631578947368421,
				"y": 0.3466666666666667
			}
		},
		{
			"class_idx": 0,
			"name": "bt",
			"points": [
				{
					"int_x": 135,
					"int_y": 87,
					"x": 0.5827067669172932,
					"y": 0.3589743589743589
				},
				{
					"int_x": 141,
					"int_y": 87,
					"x": 0.6074113856068744,
					"y": 0.3589743589743589
				},
				{
					"int_x": 141,
					"int_y": 96,
					"x": 0.6074113856068744,
					"y": 0.39384615384615385
				},
				{
					"int_x": 135,
					"int_y": 96,
					"x": 0.5827067669172932,
					"y": 0.39384615384615385
				}
			],
			"rect": {
				"h": 0.034871794871794926,
				"int_h": 10,
				"int_w": 7,
				"int_x": 135,
				"int_y": 87,
				"w": 0.02470461868958118,
				"x": 0.5827067669172932,
				"y": 0.3589743589743589
			}
		},
		{
			"class_idx": 0,
			"name": "bt",
			"points": [
				{
					"int_x": 125,
					"int_y": 78,
					"x": 0.5408163265306122,
					"y": 0.32153846153846155
				},
				{
					"int_x": 133,
					"int_y": 78,
					"x": 0.5719656283566058,
					"y": 0.32153846153846155
				},
				{
					"int_x": 133,
					"int_y": 84,
					"x": 0.5719656283566058,
					"y": 0.3471794871794872
				},
				{
					"int_x": 125,
					"int_y": 84,
					"x": 0.5408163265306122,
					"y": 0.3471794871794872
				}
			],
			"rect": {
				"h": 0.02564102564102566,
				"int_h": 7,
				"int_w": 9,
				"int_x": 125,
				"int_y": 78,
				"w": 0.031149301825993625,
				"x": 0.5408163265306122,
				"y": 0.32153846153846155
			}
		},
		{
			"class_idx": 0,
			"name": "bt",
			"points": [
				{
					"int_x": 117,
					"int_y": 77,
					"x": 0.5032223415682062,
					"y": 0.31846153846153846
				},
				{
					"int_x": 123,
					"int_y": 77,
					"x": 0.5300751879699248,
					"y": 0.31846153846153846
				},
				{
					"int_x": 123,
					"int_y": 84,
					"x": 0.5300751879699248,
					"y": 0.34615384615384615
				},
				{
					"int_x": 117,
					"int_y": 84,
					"x": 0.5032223415682062,
					"y": 0.34615384615384615
				}
			],
			"rect": {
				"h": 0.027692307692307683,
				"int_h": 8,
				"int_w": 7,
				"int_x": 117,
				"int_y": 77,
				"w": 0.02685284640171859,
				"x": 0.5032223415682062,
				"y": 0.31846153846153846
			}
		},
		{
			"class_idx": 0,
			"name": "bt",
			"points": [
				{
					"int_x": 36,
					"int_y": 55,
					"x": 0.15628356605800214,
					"y": 0.2246153846153846
				},
				{
					"int_x": 47,
					"int_y": 55,
					"x": 0.20461868958109558,
					"y": 0.2246153846153846
				},
				{
					"int_x": 47,
					"int_y": 64,
					"x": 0.20461868958109558,
					"y": 0.26153846153846155
				},
				{
					"int_x": 36,
					"int_y": 64,
					"x": 0.15628356605800214,
					"y": 0.26153846153846155
				}
			],
			"rect": {
				"h": 0.03692307692307695,
				"int_h": 10,
				"int_w": 12,
				"int_x": 36,
				"int_y": 55,
				"w": 0.04833512352309344,
				"x": 0.15628356605800214,
				"y": 0.2246153846153846
			}
		},
		{
			"class_idx": 0,
			"name": "bt",
			"points": [
				{
					"int_x": 51,
					"int_y": 85,
					"x": 0.21911922663802363,
					"y": 0.34923076923076923
				},
				{
					"int_x": 63,
					"int_y": 85,
					"x": 0.2706766917293233,
					"y": 0.34923076923076923
				},
				{
					"int_x": 63,
					"int_y": 93,
					"x": 0.2706766917293233,
					"y": 0.3830769230769231
				},
				{
					"int_x": 51,
					"int_y": 93,
					"x": 0.21911922663802363,
					"y": 0.3830769230769231
				}
			],
			"rect": {
				"h": 0.03384615384615386,
				"int_h": 9,
				"int_w": 13,
				"int_x": 51,
				"int_y": 85,
				"w": 0.05155746509129966,
				"x": 0.21911922663802363,
				"y": 0.34923076923076923
			}
		},
		{
			"class_idx": 0,
			"name": "bt",
			"points": [
				{
					"int_x": 57,
					"int_y": 94,
					"x": 0.24704618689581095,
					"y": 0.3887179487179487
				},
				{
					"int_x": 72,
					"int_y": 94,
					"x": 0.3114930182599356,
					"y": 0.3887179487179487
				},
				{
					"int_x": 72,
					"int_y": 107,
					"x": 0.3114930182599356,
					"y": 0.44
				},
				{
					"int_x": 57,
					"int_y": 107,
					"x": 0.24704618689581095,
					"y": 0.44
				}
			],
			"rect": {
				"h": 0.05128205128205132,
				"int_h": 14,
				"int_w": 16,
				"int_x": 57,
				"int_y": 94,
				"w": 0.06444683136412463,
				"x": 0.24704618689581095,
				"y": 0.3887179487179487
			}
		},
		{
			"class_idx": 0,
			"name": "bt",
			"points": [
				{
					"int_x": 38,
					"int_y": 92,
					"x": 0.1627282491944146,
					"y": 0.37743589743589745
				},
				{
					"int_x": 45,
					"int_y": 92,
					"x": 0.19387755102040816,
					"y": 0.37743589743589745
				},
				{
					"int_x": 45,
					"int_y": 99,
					"x": 0.19387755102040816,
					"y": 0.4082051282051282
				},
				{
					"int_x": 38,
					"int_y": 99,
					"x": 0.1627282491944146,
					"y": 0.4082051282051282
				}
			],
			"rect": {
				"h": 0.03076923076923077,
				"int_h": 8,
				"int_w": 8,
				"int_x": 38,
				"int_y": 92,
				"w": 0.03114930182599357,
				"x": 0.1627282491944146,
				"y": 0.37743589743589745
			}
		},
		{
			"class_idx": 0,
			"name": "bt",
			"points": [
				{
					"int_x": 36,
					"int_y": 101,
					"x": 0.15628356605800214,
					"y": 0.41384615384615386
				},
				{
					"int_x": 44,
					"int_y": 101,
					"x": 0.1917293233082707,
					"y": 0.41384615384615386
				},
				{
					"int_x": 44,
					"int_y": 107,
					"x": 0.1917293233082707,
					"y": 0.4394871794871795
				},
				{
					"int_x": 36,
					"int_y": 107,
					"x": 0.15628356605800214,
					"y": 0.4394871794871795
				}
			],
			"rect": {
				"h": 0.02564102564102566,
				"int_h": 7,
				"int_w": 9,
				"int_x": 36,
				"int_y": 101,
				"w": 0.03544575725026855,
				"x": 0.15628356605800214,
				"y": 0.41384615384615386
			}
		},
		{
			"class_idx": 0,
			"name": "bt",
			"points": [
				{
					"int_x": 49,
					"int_y": 97,
					"x": 0.21052631578947367,
					"y": 0.39897435897435896
				},
				{
					"int_x": 56,
					"int_y": 97,
					"x": 0.24060150375939848,
					"y": 0.39897435897435896
				},
				{
					"int_x": 56,
					"int_y": 104,
					"x": 0.24060150375939848,
					"y": 0.4276923076923077
				},
				{
					"int_x": 49,
					"int_y": 104,
					"x": 0.21052631578947367,
					"y": 0.4276923076923077
				}
			],
			"rect": {
				"h": 0.02871794871794875,
				"int_h": 8,
				"int_w": 8,
				"int_x": 49,
				"int_y": 97,
				"w": 0.03007518796992481,
				"x": 0.21052631578947367,
				"y": 0.39897435897435896
			}
		},
		{
			"class_idx": 0,
			"name": "bt",
			"points": [
				{
					"int_x": 52,
					"int_y": 111,
					"x": 0.22502685284640173,
					"y": 0.4564102564102564
				},
				{
					"int_x": 61,
					"int_y": 111,
					"x": 0.2647690655209452,
					"y": 0.4564102564102564
				},
				{
					"int_x": 61,
					"int_y": 118,
					"x": 0.2647690655209452,
					"y": 0.48717948717948717
				},
				{
					"int_x": 52,
					"int_y": 118,
					"x": 0.22502685284640173,
					"y": 0.48717948717948717
				}
			],
			"rect": {
				"h": 0.03076923076923077,
				"int_h": 8,
				"int_w": 10,
				"int_x": 52,
				"int_y": 111,
				"w": 0.039742212674543476,
				"x": 0.22502685284640173,
				"y": 0.4564102564102564
			}
		},
		{
			"class_idx": 0,
			"name": "bt",
			"points": [
				{
					"int_x": 62,
					"int_y": 110,
					"x": 0.2679914070891515,
					"y": 0.4523076923076923
				},
				{
					"int_x": 73,
					"int_y": 110,
					"x": 0.3141783029001074,
					"y": 0.4523076923076923
				},
				{
					"int_x": 73,
					"int_y": 118,
					"x": 0.3141783029001074,
					"y": 0.4851282051282051
				},
				{
					"int_x": 62,
					"int_y": 118,
					"x": 0.2679914070891515,
					"y": 0.4851282051282051
				}
			],
			"rect": {
				"h": 0.03282051282051279,
				"int_h": 9,
				"int_w": 12,
				"int_x": 62,
				"int_y": 110,
				"w": 0.04618689581095592,
				"x": 0.2679914070891515,
				"y": 0.4523076923076923
			}
		},
		{
			"class_idx": 0,
			"name": "bt",
			"points": [
				{
					"int_x": 75,
					"int_y": 92,
					"x": 0.32438238453276047,
					"y": 0.38
				},
				{
					"int_x": 88,
					"int_y": 92,
					"x": 0.37808807733619765,
					"y": 0.38
				},
				{
					"int_x": 88,
					"int_y": 114,
					"x": 0.37808807733619765,
					"y": 0.4671794871794872
				},
				{
					"int_x": 75,
					"int_y": 114,
					"x": 0.32438238453276047,
					"y": 0.4671794871794872
				}
			],
			"rect": {
				"h": 0.0871794871794872,
				"int_h": 23,
				"int_w": 14,
				"int_x": 75,
				"int_y": 92,
				"w": 0.05370569280343718,
				"x": 0.32438238453276047,
				"y": 0.38
			}
		},
		{
			"class_idx": 0,
			"name": "bt",
			"points": [
				{
					"int_x": 99,
					"int_y": 107,
					"x": 0.4253490870032224,
					"y": 0.43948717948717947
				},
				{
					"int_x": 114,
					"int_y": 107,
					"x": 0.4897959183673469,
					"y": 0.43948717948717947
				},
				{
					"int_x": 114,
					"int_y": 122,
					"x": 0.4897959183673469,
					"y": 0.502051282051282
				},
				{
					"int_x": 99,
					"int_y": 122,
					"x": 0.4253490870032224,
					"y": 0.502051282051282
				}
			],
			"rect": {
				"h": 0.06256410256410255,
				"int_h": 16,
				"int_w": 16,
				"int_x": 99,
				"int_y": 107,
				"w": 0.06444683136412455,
				"x": 0.4253490870032224,
				"y": 0.43948717948717947
			}
		},
		{
			"class_idx": 0,
			"name": "bt",
			"points": [
				{
					"int_x": 76,
					"int_y": 124,
					"x": 0.3292158968850698,
					"y": 0.5097435897435897
				},
				{
					"int_x": 87,
					"int_y": 124,
					"x": 0.3732545649838883,
					"y": 0.5097435897435897
				},
				{
					"int_x": 87,
					"int_y": 135,
					"x": 0.3732545649838883,
					"y": 0.5548717948717948
				},
				{
					"int_x": 76,
					"int_y": 135,
					"x": 0.3292158968850698,
					"y": 0.5548717948717948
				}
			],
			"rect": {
				"h": 0.045128205128205146,
				"int_h": 12,
				"int_w": 12,
				"int_x": 76,
				"int_y": 124,
				"w": 0.04403866809881851,
				"x": 0.3292158968850698,
				"y": 0.5097435897435897
			}
		},
		{
			"class_idx": 0,
			"name": "bt",
			"points": [
				{
					"int_x": 30,
					"int_y": 114,
					"x": 0.12728249194414606,
					"y": 0.46871794871794875
				},
				{
					"int_x": 44,
					"int_y": 114,
					"x": 0.18850698174006444,
					"y": 0.46871794871794875
				},
				{
					"int_x": 44,
					"int_y": 120,
					"x": 0.18850698174006444,
					"y": 0.49538461538461537
				},
				{
					"int_x": 30,
					"int_y": 120,
					"x": 0.12728249194414606,
					"y": 0.49538461538461537
				}
			],
			"rect": {
				"h": 0.026666666666666616,
				"int_h": 7,
				"int_w": 15,
				"int_x": 30,
				"int_y": 114,
				"w": 0.06122448979591838,
				"x": 0.12728249194414606,
				"y": 0.46871794871794875
			}
		},
		{
			"class_idx": 0,
			"name": "bt",
			"points": [
				{
					"int_x": 141,
					"int_y": 124,
					"x": 0.6095596133190118,
					"y": 0.5102564102564103
				},
				{
					"int_x": 150,
					"int_y": 124,
					"x": 0.6471535982814178,
					"y": 0.5102564102564103
				},
				{
					"int_x": 150,
					"int_y": 133,
					"x": 0.6471535982814178,
					"y": 0.5482051282051282
				},
				{
					"int_x": 141,
					"int_y": 133,
					"x": 0.6095596133190118,
					"y": 0.5482051282051282
				}
			],
			"rect": {
				"h": 0.0379487179487179,
				"int_h": 10,
				"int_w": 10,
				"int_x": 141,
				"int_y": 124,
				"w": 0.03759398496240607,
				"x": 0.6095596133190118,
				"y": 0.5102564102564103
			}
		},
		{
			"class_idx": 0,
			"name": "bt",
			"points": [
				{
					"int_x": 137,
					"int_y": 119,
					"x": 0.5923737916219118,
					"y": 0.49128205128205127
				},
				{
					"int_x": 143,
					"int_y": 119,
					"x": 0.617078410311493,
					"y": 0.49128205128205127
				},
				{
					"int_x": 143,
					"int_y": 125,
					"x": 0.617078410311493,
					"y": 0.5138461538461538
				},
				{
					"int_x": 137,
					"int_y": 125,
					"x": 0.5923737916219118,
					"y": 0.5138461538461538
				}
			],
			"rect": {
				"h": 0.022564102564102573,
				"int_h": 7,
				"int_w": 7,
				"int_x": 137,
				"int_y": 119,
				"w": 0.02470461868958118,
				"x": 0.5923737916219118,
				"y": 0.49128205128205127
			}
		},
		{
			"class_idx": 0,
			"name": "bt",
			"points": [
				{
					"int_x": 124,
					"int_y": 143,
					"x": 0.5338345864661654,
					"y": 0.5897435897435898
				},
				{
					"int_x": 140,
					"int_y": 143,
					"x": 0.6047261009667025,
					"y": 0.5897435897435898
				},
				{
					"int_x": 140,
					"int_y": 152,
					"x": 0.6047261009667025,
					"y": 0.6266666666666666
				},
				{
					"int_x": 124,
					"int_y": 152,
					"x": 0.5338345864661654,
					"y": 0.6266666666666666
				}
			],
			"rect": {
				"h": 0.036923076923076836,
				"int_h": 10,
				"int_w": 17,
				"int_x": 124,
				"int_y": 143,
				"w": 0.0708915145005371,
				"x": 0.5338345864661654,
				"y": 0.5897435897435898
			}
		},
		{
			"class_idx": 0,
			"name": "bt",
			"points": [
				{
					"int_x": 117,
					"int_y": 134,
					"x": 0.5059076262083781,
					"y": 0.5512820512820512
				},
				{
					"int_x": 133,
					"int_y": 134,
					"x": 0.5725026852846402,
					"y": 0.5512820512820512
				},
				{
					"int_x": 133,
					"int_y": 141,
					"x": 0.5725026852846402,
					"y": 0.581025641025641
				},
				{
					"int_x": 117,
					"int_y": 141,
					"x": 0.5059076262083781,
					"y": 0.581025641025641
				}
			],
			"rect": {
				"h": 0.029743589743589816,
				"int_h": 8,
				"int_w": 17,
				"int_x": 117,
				"int_y": 134,
				"w": 0.06659505907626206,
				"x": 0.5059076262083781,
				"y": 0.5512820512820512
			}
		},
		{
			"class_idx": 0,
			"name": "bt",
			"points": [
				{
					"int_x": 115,
					"int_y": 112,
					"x": 0.4967776584317938,
					"y": 0.4594871794871795
				},
				{
					"int_x": 124,
					"int_y": 112,
					"x": 0.5365198711063373,
					"y": 0.4594871794871795
				},
				{
					"int_x": 124,
					"int_y": 119,
					"x": 0.5365198711063373,
					"y": 0.49025641025641026
				},
				{
					"int_x": 115,
					"int_y": 119,
					"x": 0.4967776584317938,
					"y": 0.49025641025641026
				}
			],
			"rect": {
				"h": 0.03076923076923077,
				"int_h": 8,
				"int_w": 10,
				"int_x": 115,
				"int_y": 112,
				"w": 0.039742212674543476,
				"x": 0.4967776584317938,
				"y": 0.4594871794871795
			}
		},
		{
			"class_idx": 0,
			"name": "bt",
			"points": [
				{
					"int_x": 120,
					"int_y": 104,
					"x": 0.5155746509129968,
					"y": 0.4287179487179487
				},
				{
					"int_x": 125,
					"int_y": 104,
					"x": 0.5392051557465092,
					"y": 0.4287179487179487
				},
				{
					"int_x": 125,
					"int_y": 111,
					"x": 0.5392051557465092,
					"y": 0.45743589743589746
				},
				{
					"int_x": 120,
					"int_y": 111,
					"x": 0.5155746509129968,
					"y": 0.45743589743589746
				}
			],
			"rect": {
				"h": 0.02871794871794875,
				"int_h": 8,
				"int_w": 6,
				"int_x": 120,
				"int_y": 104,
				"w": 0.023630504833512367,
				"x": 0.5155746509129968,
				"y": 0.4287179487179487
			}
		},
		{
			"class_idx": 0,
			"name": "bt",
			"points": [
				{
					"int_x": 134,
					"int_y": 98,
					"x": 0.577873254564984,
					"y": 0.4030769230769231
				},
				{
					"int_x": 142,
					"int_y": 98,
					"x": 0.6100966702470462,
					"y": 0.4030769230769231
				},
				{
					"int_x": 142,
					"int_y": 111,
					"x": 0.6100966702470462,
					"y": 0.4584615384615385
				},
				{
					"int_x": 134,
					"int_y": 111,
					"x": 0.577873254564984,
					"y": 0.4584615384615385
				}
			],
			"rect": {
				"h": 0.055384615384615365,
				"int_h": 14,
				"int_w": 9,
				"int_x": 134,
				"int_y": 98,
				"w": 0.03222341568206222,
				"x": 0.577873254564984,
				"y": 0.4030769230769231
			}
		},
		{
			"class_idx": 0,
			"name": "bt",
			"points": [
				{
					"int_x": 126,
					"int_y": 93,
					"x": 0.5413533834586466,
					"y": 0.3835897435897436
				},
				{
					"int_x": 131,
					"int_y": 93,
					"x": 0.5628356605800215,
					"y": 0.3835897435897436
				},
				{
					"int_x": 131,
					"int_y": 100,
					"x": 0.5628356605800215,
					"y": 0.41025641025641024
				},
				{
					"int_x": 126,
					"int_y": 100,
					"x": 0.5413533834586466,
					"y": 0.41025641025641024
				}
			],
			"rect": {
				"h": 0.026666666666666616,
				"int_h": 8,
				"int_w": 6,
				"int_x": 126,
				"int_y": 93,
				"w": 0.02148227712137496,
				"x": 0.5413533834586466,
				"y": 0.3835897435897436
			}
		},
		{
			"class_idx": 0,
			"name": "bt",
			"points": [
				{
					"int_x": 144,
					"int_y": 148,
					"x": 0.6197636949516648,
					"y": 0.6076923076923076
				},
				{
					"int_x": 149,
					"int_y": 148,
					"x": 0.6433941997851772,
					"y": 0.6076923076923076
				},
				{
					"int_x": 149,
					"int_y": 154,
					"x": 0.6433941997851772,
					"y": 0.6353846153846153
				},
				{
					"int_x": 144,
					"int_y": 154,
					"x": 0.6197636949516648,
					"y": 0.6353846153846153
				}
			],
			"rect": {
				"h": 0.027692307692307683,
				"int_h": 7,
				"int_w": 6,
				"int_x": 144,
				"int_y": 148,
				"w": 0.023630504833512367,
				"x": 0.6197636949516648,
				"y": 0.6076923076923076
			}
		},
		{
			"class_idx": 0,
			"name": "bt",
			"points": [
				{
					"int_x": 153,
					"int_y": 148,
					"x": 0.6611170784103114,
					"y": 0.6082051282051282
				},
				{
					"int_x": 162,
					"int_y": 148,
					"x": 0.6987110633727175,
					"y": 0.6082051282051282
				},
				{
					"int_x": 162,
					"int_y": 155,
					"x": 0.6987110633727175,
					"y": 0.6369230769230769
				},
				{
					"int_x": 153,
					"int_y": 155,
					"x": 0.6611170784103114,
					"y": 0.6369230769230769
				}
			],
			"rect": {
				"h": 0.02871794871794875,
				"int_h": 8,
				"int_w": 10,
				"int_x": 153,
				"int_y": 148,
				"w": 0.03759398496240607,
				"x": 0.6611170784103114,
				"y": 0.6082051282051282
			}
		},
		{
			"class_idx": 0,
			"name": "bt",
			"points": [
				{
					"int_x": 140,
					"int_y": 178,
					"x": 0.6052631578947368,
					"y": 0.7333333333333333
				},
				{
					"int_x": 147,
					"int_y": 178,
					"x": 0.6342642320085928,
					"y": 0.7333333333333333
				},
				{
					"int_x": 147,
					"int_y": 184,
					"x": 0.6342642320085928,
					"y": 0.7558974358974359
				},
				{
					"int_x": 140,
					"int_y": 184,
					"x": 0.6052631578947368,
					"y": 0.7558974358974359
				}
			],
			"rect": {
				"h": 0.022564102564102573,
				"int_h": 7,
				"int_w": 8,
				"int_x": 140,
				"int_y": 178,
				"w": 0.029001074113855996,
				"x": 0.6052631578947368,
				"y": 0.7333333333333333
			}
		},
		{
			"class_idx": 0,
			"name": "bt",
			"points": [
				{
					"int_x": 122,
					"int_y": 176,
					"x": 0.5257787325456499,
					"y": 0.7261538461538461
				},
				{
					"int_x": 128,
					"int_y": 176,
					"x": 0.5526315789473685,
					"y": 0.7261538461538461
				},
				{
					"int_x": 128,
					"int_y": 183,
					"x": 0.5526315789473685,
					"y": 0.7528205128205128
				},
				{
					"int_x": 122,
					"int_y": 183,
					"x": 0.5257787325456499,
					"y": 0.7528205128205128
				}
			],
			"rect": {
				"h": 0.026666666666666616,
				"int_h": 8,
				"int_w": 7,
				"int_x": 122,
				"int_y": 176,
				"w": 0.02685284640171859,
				"x": 0.5257787325456499,
				"y": 0.7261538461538461
			}
		},
		{
			"class_idx": 0,
			"name": "bt",
			"points": [
				{
					"int_x": 130,
					"int_y": 175,
					"x": 0.562298603651987,
					"y": 0.7210256410256409
				},
				{
					"int_x": 136,
					"int_y": 175,
					"x": 0.5870032223415682,
					"y": 0.7210256410256409
				},
				{
					"int_x": 136,
					"int_y": 181,
					"x": 0.5870032223415682,
					"y": 0.7456410256410256
				},
				{
					"int_x": 130,
					"int_y": 181,
					"x": 0.562298603651987,
					"y": 0.7456410256410256
				}
			],
			"rect": {
				"h": 0.024615384615384706,
				"int_h": 7,
				"int_w": 7,
				"int_x": 130,
				"int_y": 175,
				"w": 0.02470461868958118,
				"x": 0.562298603651987,
				"y": 0.7210256410256409
			}
		},
		{
			"class_idx": 0,
			"name": "bt",
			"points": [
				{
					"int_x": 154,
					"int_y": 176,
					"x": 0.6632653061224489,
					"y": 0.7261538461538461
				},
				{
					"int_x": 160,
					"int_y": 176,
					"x": 0.6879699248120301,
					"y": 0.7261538461538461
				},
				{
					"int_x": 160,
					"int_y": 185,
					"x": 0.6879699248120301,
					"y": 0.7610256410256411
				},
				{
					"int_x": 154,
					"int_y": 185,
					"x": 0.6632653061224489,
					"y": 0.7610256410256411
				}
			],
			"rect": {
				"h": 0.034871794871794926,
				"int_h": 10,
				"int_w": 7,
				"int_x": 154,
				"int_y": 176,
				"w": 0.02470461868958118,
				"x": 0.6632653061224489,
				"y": 0.7261538461538461
			}
		},
		{
			"class_idx": 0,
			"name": "bt",
			"points": [
				{
					"int_x": 152,
					"int_y": 191,
					"x": 0.6557465091299678,
					"y": 0.7876923076923077
				},
				{
					"int_x": 158,
					"int_y": 191,
					"x": 0.6825993555316864,
					"y": 0.7876923076923077
				},
				{
					"int_x": 158,
					"int_y": 198,
					"x": 0.6825993555316864,
					"y": 0.8143589743589743
				},
				{
					"int_x": 152,
					"int_y": 198,
					"x": 0.6557465091299678,
					"y": 0.8143589743589743
				}
			],
			"rect": {
				"h": 0.026666666666666616,
				"int_h": 8,
				"int_w": 7,
				"int_x": 152,
				"int_y": 191,
				"w": 0.02685284640171859,
				"x": 0.6557465091299678,
				"y": 0.7876923076923077
			}
		},
		{
			"class_idx": 0,
			"name": "bt",
			"points": [
				{
					"int_x": 175,
					"int_y": 195,
					"x": 0.7524167561761547,
					"y": 0.8015384615384615
				},
				{
					"int_x": 188,
					"int_y": 195,
					"x": 0.8114930182599355,
					"y": 0.8015384615384615
				},
				{
					"int_x": 188,
					"int_y": 202,
					"x": 0.8114930182599355,
					"y": 0.8333333333333333
				},
				{
					"int_x": 175,
					"int_y": 202,
					"x": 0.7524167561761547,
					"y": 0.8333333333333333
				}
			],
			"rect": {
				"h": 0.031794871794871726,
				"int_h": 8,
				"int_w": 14,
				"int_x": 175,
				"int_y": 195,
				"w": 0.059076262083780806,
				"x": 0.7524167561761547,
				"y": 0.8015384615384615
			}
		},
		{
			"class_idx": 0,
			"name": "bt",
			"points": [
				{
					"int_x": 98,
					"int_y": 142,
					"x": 0.42105263157894735,
					"y": 0.5841025641025641
				},
				{
					"int_x": 107,
					"int_y": 142,
					"x": 0.46186895810955964,
					"y": 0.5841025641025641
				},
				{
					"int_x": 107,
					"int_y": 151,
					"x": 0.46186895810955964,
					"y": 0.622051282051282
				},
				{
					"int_x": 98,
					"int_y": 151,
					"x": 0.42105263157894735,
					"y": 0.622051282051282
				}
			],
			"rect": {
				"h": 0.0379487179487179,
				"int_h": 10,
				"int_w": 10,
				"int_x": 98,
				"int_y": 142,
				"w": 0.04081632653061229,
				"x": 0.42105263157894735,
				"y": 0.5841025641025641
			}
		},
		{
			"class_idx": 0,
			"name": "bt",
			"points": [
				{
					"int_x": 87,
					"int_y": 122,
					"x": 0.37593984962406013,
					"y": 0.504102564102564
				},
				{
					"int_x": 97,
					"int_y": 122,
					"x": 0.4167561761546724,
					"y": 0.504102564102564
				},
				{
					"int_x": 97,
					"int_y": 134,
					"x": 0.4167561761546724,
					"y": 0.5502564102564103
				},
				{
					"int_x": 87,
					"int_y": 134,
					"x": 0.37593984962406013,
					"y": 0.5502564102564103
				}
			],
			"rect": {
				"h": 0.04615384615384621,
				"int_h": 13,
				"int_w": 11,
				"int_x": 87,
				"int_y": 122,
				"w": 0.04081632653061229,
				"x": 0.37593984962406013,
				"y": 0.504102564102564
			}
		},
		{
			"class_idx": 0,
			"name": "bt",
			"points": [
				{
					"int_x": 74,
					"int_y": 113,
					"x": 0.31686358754027927,
					"y": 0.4630769230769231
				},
				{
					"int_x": 85,
					"int_y": 113,
					"x": 0.3662728249194414,
					"y": 0.4630769230769231
				},
				{
					"int_x": 85,
					"int_y": 119,
					"x": 0.3662728249194414,
					"y": 0.4907692307692308
				},
				{
					"int_x": 74,
					"int_y": 119,
					"x": 0.31686358754027927,
					"y": 0.4907692307692308
				}
			],
			"rect": {
				"h": 0.027692307692307683,
				"int_h": 7,
				"int_w": 12,
				"int_x": 74,
				"int_y": 113,
				"w": 0.04940923737916214,
				"x": 0.31686358754027927,
				"y": 0.4630769230769231
			}
		}
	],
	"timestamp": 1753148452,
	"version": "1.10.27-1"
}
